bor/__init__.py
bor/bundle.py
bor/cli.py
bor/core.py
bor/decorators.py
bor/exceptions.py
bor/hash_utils.py
bor/store.py
bor/subproofs.py
bor/verify.py
examples/__init__.py
examples/demo.py
examples/demo_add_square.py
examples/demo_pipeline.py
examples/demo_randomness_guard.py
examples/demo_reconcile.py
examples/demo_verify.py
tests/__init__.py
tests/test_core.py
tests/test_decorators.py
tests/test_determinism_suite.py
tests/test_e2_remaining_subproofs.py
tests/test_e_subproofs_bundle.py
tests/test_f_bundle_verify_and_trace.py
tests/test_hash_utils.py
tests/test_p0_init.py
tests/test_p1_steps.py
tests/test_p2_master.py
tests/test_p3_verify.py
tests/test_p4_persistence.py
tests/test_register_hash.py
tests/test_store.py
tests/test_verify.py
bor_sdk-1.0.0.dist-info/LICENSE
bor_sdk-1.0.0.dist-info/METADATA
bor_sdk-1.0.0.dist-info/WHEEL
bor_sdk-1.0.0.dist-info/entry_points.txt
bor_sdk-1.0.0.dist-info/top_level.txt
bor_sdk-1.0.0.dist-info/RECORD
