Metadata-Version: 2.1
Name: bor-sdk
Version: 1.0.0
Summary: BoR-Proof SDK — Deterministic, Replay-Verifiable Proof of Reasoning
Author: Kushagra Bhatnagar
Author-email: Kushagra Bhatnagar <bhatnagar.kushagra.m@gmail.com>
License: MIT
Project-URL: Homepage, https://github.com/kushagrab21/BoR-proof-SDK
Project-URL: Documentation, https://github.com/kushagrab21/BoR-proof-SDK#readme
Project-URL: Issues, https://github.com/kushagrab21/BoR-proof-SDK/issues
Project-URL: Repository, https://github.com/kushagrab21/BoR-proof-SDK
Keywords: deterministic-ai,reproducibility,proof,hashing,bor,reasoning,verification
Classifier: Development Status :: 5 - Production/Stable
Classifier: Intended Audience :: Developers
Classifier: Intended Audience :: Science/Research
Classifier: License :: OSI Approved :: MIT License
Classifier: Operating System :: OS Independent
Classifier: Programming Language :: Python :: 3
Classifier: Programming Language :: Python :: 3.9
Classifier: Programming Language :: Python :: 3.10
Classifier: Programming Language :: Python :: 3.11
Classifier: Programming Language :: Python :: 3.12
Classifier: Topic :: Scientific/Engineering :: Artificial Intelligence
Classifier: Topic :: Software Development :: Libraries :: Python Modules
Requires-Python: >=3.9
License-File: LICENSE
Provides-Extra: dev
Requires-Dist: pytest>=7.0.0; extra == "dev"
Requires-Dist: black>=23.0.0; extra == "dev"
